lagsync/__init__.py
lagsync/lagsync.py
lagsync-1.2.1.dist-info/LICENSE
lagsync-1.2.1.dist-info/METADATA
lagsync-1.2.1.dist-info/WHEEL
lagsync-1.2.1.dist-info/entry_points.txt
lagsync-1.2.1.dist-info/top_level.txt
lagsync-1.2.1.dist-info/RECORD
