Metadata-Version: 2.1
Name: lagsync
Version: 1.2.1
Summary: A rsync based backup utility for laggy connections
Author-email: bluePlatinum <jukic.rok@gmail.com>
License: MIT License
Project-URL: Homepage, https://github.com/bluePlatinum/lagsync
Project-URL: Issues, https://github.com/bluePlatinum/lagsync/issues
Classifier: Programming Language :: Python :: 3
Classifier: License :: OSI Approved :: MIT License
Classifier: Operating System :: OS Independent
Classifier: Environment :: Console
Classifier: Intended Audience :: System Administrators
Classifier: Natural Language :: English
Classifier: Topic :: System :: Archiving :: Backup
Classifier: Topic :: Utilities
Requires-Python: >=3.7
License-File: LICENSE
